LICENSE
MANIFEST.in
README.md
environment.yml
requirements.txt
setup.py
version
cambriantools/_C.py
cambriantools/__init__.py
cambriantools/dicts.py
cambriantools/files.py
cambriantools/lists.py
cambriantools/pdfs.py
cambriantools/strings.py
cambriantools.egg-info/PKG-INFO
cambriantools.egg-info/SOURCES.txt
cambriantools.egg-info/dependency_links.txt
cambriantools.egg-info/requires.txt
cambriantools.egg-info/top_level.txt