Metadata-Version: 2.1
Name: cambriantools
Version: 0.0.6
Summary: generic description
Author: Oscar Pimentel Fuentes
Author-email: oscarlo.pimentel@gmail.com
License: MIT licence
Keywords: experimental
Platform: UNKNOWN
Classifier: Programming Language :: Python :: 3
Classifier: License :: OSI Approved :: MIT License
Classifier: Operating System :: OS Independent
Requires-Python: >=3.10
License-File: LICENSE
